licant/__init__.py
licant/__main__.py
licant/cache.py
licant/cli.py
licant/core.py
licant/cxx_make.py
licant/cxx_modules.py
licant/install.py
licant/java_make.py
licant/libs.py
licant/licant_libs.py
licant/make.py
licant/modules.py
licant/scripter.py
licant/solver.py
licant/util.py
licant-1.15.0.data/scripts/licant-libs
licant-1.15.0.dist-info/METADATA
licant-1.15.0.dist-info/WHEEL
licant-1.15.0.dist-info/top_level.txt
licant-1.15.0.dist-info/RECORD
