Metadata-Version: 2.1
Name: licant
Version: 1.15.0
Summary: licant make system
Home-page: https://github.com/mirmik/licant
Author: Sorokin Nikolay
Author-email: mirmikns@yandex.ru
License: MIT
Keywords: testing,make
Platform: UNKNOWN
